Workbook

Sheet Dashboard
A1: Used Car in Sweden – 10-Year Total Cost of Ownership Dashboard
A2: Update yellow cells on the Inputs and Maintenance sheets. All values below update automatically. | N2: Month | O2: Monthly operating cost | Q2: Month | R2: Cumulative nominal cost | X2: Category | Y2: Cost | AA2: Month | AB2: Cumulative discounted cost
N3: =Cashflow!B7 -> 46143 | O3: =-Cashflow!I7 -> 2579.302 | Q3: =Cashflow!B7 -> 46143 | R3: =Cashflow!L7 -> 68579.302 | X3: Purchase price | Y3: =Inputs!$B$4 -> 66000 | AA3: =Cashflow!B7 -> 46143 | AB3: =Cashflow!M7 -> 68568.836
A4: Car market price | C4: Total undiscounted 10-year cost | E4: Total discounted cost / NPV | G4: Average monthly cost | J4: Key assumptions | N4: =Cashflow!B8 -> 46174 | O4: =-Cashflow!I8 -> 2082.553 | Q4: =Cashflow!B8 -> 46174 | R4: =Cashflow!L8 -> 70661.855 | X4: Fuel | Y4: =-SUM(Cashflow!$E$6:$E$126) -> 159417.49 | AA4: =Cashflow!B8 -> 46174 | AB4: =Cashflow!M8 -> 70634.523
A5: =Inputs!$B$4 -> 66000 | C5: =-SUM(Cashflow!$I$6:$I$126) -> 402722.59 | E5: =-SUM(Cashflow!$K$6:$K$126) -> 331847.88 | G5: =C5/Inputs!$B$21 -> 3356.0216 | J5: Expected monthly mileage | K5: =Inputs!$B$7 -> 1200 | L5: km/month | N5: =Cashflow!B9 -> 46204 | O5: =-Cashflow!I9 -> 2086.8427 | Q5: =Cashflow!B9 -> 46204 | R5: =Cashflow!L9 -> 72748.698 | X5: Insurance | Y5: =-SUM(Cashflow!$F$6:$F$126) -> 123173.85 | AA5: =Cashflow!B9 -> 46204 | AB5: =Cashflow!M9 -> 72696.066
J6: Annual inflation rate | K6: =Inputs!$B$17 -> 0.025 | N6: =Cashflow!B10 -> 46235 | O6: =-Cashflow!I10 -> 3906.018 | Q6: =Cashflow!B10 -> 46235 | R6: =Cashflow!L10 -> 76654.716 | X6: Tax | Y6: =-SUM(Cashflow!$G$6:$G$126) -> 14354.333 | AA6: =Cashflow!B10 -> 46235 | AB6: =Cashflow!M10 -> 76539.073
J7: Annual discount rate | K7: =Inputs!$B$18 -> 0.05 | N7: =Cashflow!B11 -> 46266 | O7: =-Cashflow!I11 -> 4419.2346 | Q7: =Cashflow!B11 -> 46266 | R7: =Cashflow!L11 -> 81073.95 | X7: Maintenance | Y7: =-SUM(Cashflow!$H$6:$H$126) -> 39776.918 | AA7: =Cashflow!B11 -> 46266 | AB7: =Cashflow!M11 -> 80869.375
A8: Total fuel cost | C8: Total insurance cost | E8: Total tax cost | G8: Total maintenance cost | J8: Fuel type | K8: =Inputs!$B$11 -> Petrol | N8: =Cashflow!B12 -> 46296 | O8: =-Cashflow!I12 -> 2099.765 | Q8: =Cashflow!B12 -> 46296 | R8: =Cashflow!L12 -> 83173.715 | AA8: =Cashflow!B12 -> 46296 | AB8: =Cashflow!M12 -> 82918.536
A9: =-SUM(Cashflow!$E$6:$E$126) -> 159417.49 | C9: =-SUM(Cashflow!$F$6:$F$126) -> 123173.85 | E9: =-SUM(Cashflow!$G$6:$G$126) -> 14354.333 | G9: =-SUM(Cashflow!$H$6:$H$126) -> 39776.918 | J9: Fuel price per litre | K9: =Inputs!$B$13 -> 15 | L9: SEK/litre | N9: =Cashflow!B13 -> 46327 | O9: =-Cashflow!I13 -> 2104.0901 | Q9: =Cashflow!B13 -> 46327 | R9: =Cashflow!L13 -> 85277.805 | AA9: =Cashflow!B13 -> 46327 | AB9: =Cashflow!M13 -> 84963.586
J10: Consumption | K10: =Inputs!$B$12 -> 6.5 | L10: L/100 km | N10: =Cashflow!B14 -> 46357 | O10: =-Cashflow!I14 -> 2108.4242 | Q10: =Cashflow!B14 -> 46357 | R10: =Cashflow!L14 -> 87386.23 | AA10: =Cashflow!B14 -> 46357 | AB10: =Cashflow!M14 -> 87004.533
N11: =Cashflow!B15 -> 46388 | O11: =-Cashflow!I15 -> 2112.7672 | Q11: =Cashflow!B15 -> 46388 | R11: =Cashflow!L15 -> 89498.997 | AA11: =Cashflow!B15 -> 46388 | AB11: =Cashflow!M15 -> 89041.386
N12: =Cashflow!B16 -> 46419 | O12: =-Cashflow!I16 -> 2117.1192 | Q12: =Cashflow!B16 -> 46419 | R12: =Cashflow!L16 -> 91616.116 | AA12: =Cashflow!B16 -> 46419 | AB12: =Cashflow!M16 -> 91074.153
N13: =Cashflow!B17 -> 46447 | O13: =-Cashflow!I17 -> 2121.4801 | Q13: =Cashflow!B17 -> 46447 | R13: =Cashflow!L17 -> 93737.596 | AA13: =Cashflow!B17 -> 46447 | AB13: =Cashflow!M17 -> 93102.841
N14: =Cashflow!B18 -> 46478 | O14: =-Cashflow!I18 -> 7045.85 | Q14: =Cashflow!B18 -> 46478 | R14: =Cashflow!L18 -> 100783.45 | AA14: =Cashflow!B18 -> 46478 | AB14: =Cashflow!M18 -> 99813.175
N15: =Cashflow!B19 -> 46508 | O15: =-Cashflow!I19 -> 2130.2289 | Q15: =Cashflow!B19 -> 46508 | R15: =Cashflow!L19 -> 102913.68 | AA15: =Cashflow!B19 -> 46508 | AB15: =Cashflow!M19 -> 101833.73
N16: =Cashflow!B20 -> 46539 | O16: =-Cashflow!I20 -> 2134.6168 | Q16: =Cashflow!B20 -> 46539 | R16: =Cashflow!L20 -> 105048.29 | AA16: =Cashflow!B20 -> 46539 | AB16: =Cashflow!M20 -> 103850.24
N17: =Cashflow!B21 -> 46569 | O17: =-Cashflow!I21 -> 2139.0138 | Q17: =Cashflow!B21 -> 46569 | R17: =Cashflow!L21 -> 107187.31 | AA17: =Cashflow!B21 -> 46569 | AB17: =Cashflow!M21 -> 105862.69
N18: =Cashflow!B22 -> 46600 | O18: =-Cashflow!I22 -> 2143.4198 | Q18: =Cashflow!B22 -> 46600 | R18: =Cashflow!L22 -> 109330.73 | AA18: =Cashflow!B22 -> 46600 | AB18: =Cashflow!M22 -> 107871.12
N19: =Cashflow!B23 -> 46631 | O19: =-Cashflow!I23 -> 2147.8349 | Q19: =Cashflow!B23 -> 46631 | R19: =Cashflow!L23 -> 111478.56 | AA19: =Cashflow!B23 -> 46631 | AB19: =Cashflow!M23 -> 109875.51
N20: =Cashflow!B24 -> 46661 | O20: =-Cashflow!I24 -> 5265.4593 | Q20: =Cashflow!B24 -> 46661 | R20: =Cashflow!L24 -> 116744.02 | AA20: =Cashflow!B24 -> 46661 | AB20: =Cashflow!M24 -> 114769.38
N21: =Cashflow!B25 -> 46692 | O21: =-Cashflow!I25 -> 2156.6924 | Q21: =Cashflow!B25 -> 46692 | R21: =Cashflow!L25 -> 118900.71 | AA21: =Cashflow!B25 -> 46692 | AB21: =Cashflow!M25 -> 116765.74
N22: =Cashflow!B26 -> 46722 | O22: =-Cashflow!I26 -> 2161.1348 | Q22: =Cashflow!B26 -> 46722 | R22: =Cashflow!L26 -> 121061.85 | AA22: =Cashflow!B26 -> 46722 | AB22: =Cashflow!M26 -> 118758.09
... N122: =Cashflow!B126 -> 49766 | O122: =-Cashflow!I126 -> 4255.001 | Q122: =Cashflow!B126 -> 49766 | R122: =Cashflow!L126 -> 402722.59 | AA122: =Cashflow!B126 -> 49766 | AB122: =Cashflow!M126 -> 331847.88

Sheet Inputs
A1: Used Car TCO Model – Inputs & Assumptions
J2: Petrol
A3: Assumption | B3: Value | C3: Units / note | D3: Source / guidance | F3: Fuel default source | G3: URL | J3: Diesel
A4: Car market price | B4: 66000 | C4: SEK | D4: Editable purchase price / market value of the used car | F4: Sweden gasoline price | G4: https://www.globalpetrolprices.com/Sweden/gasoline_prices/ | J4: Other / user-defined
A5: Model start date | B5: =DATE(YEAR(TODAY()),MONTH(TODAY()),1) -> 46113 | C5: Month 0 / purchase date | D5: Formula uses current month as model start | F5: Sweden diesel price | G5: https://www.globalpetrolprices.com/Sweden/diesel_prices/
A6: Expected monthly mileage (user input) | B6: 1200 | C6: Leave blank to use 1,000 km/month | D6: Input may be blank | F6: Price update date | G6: 2026-04-13
A7: Effective monthly mileage | B7: =IF(B6="",1000,B6) -> 1200 | C7: km/month | D7: Formula defaults to 1,000 km if user input is blank
A8: Effective annual mileage | B8: =B7*12 -> 14400 | C8: km/year | D8: Formula = effective monthly mileage × 12
A9: Annual tax payment | B9: 1250 | C9: SEK/year | D9: Editable base annual vehicle tax
A10: Monthly insurance payment | B10: 904 | C10: SEK/month | D10: Editable base monthly insurance
A11: Fuel type | B11: Petrol | C11: Dropdown | D11: Petrol / Diesel / Other / user-defined
A12: Consumption rate | B12: 6.5 | C12: litres / 100 km | D12: Editable fuel consumption
A13: Fuel price per litre (linked) | B13: =IF(B11="Petrol",B14,IF(B11="Diesel",B15,B16)) -> 15 | C13: SEK/litre | D13: Formula linked to selected fuel type
A14: Petrol default price | B14: 15 | C14: SEK/litre | D14: Current Sweden gasoline price, updated 2026-04-13
A15: Diesel default price | B15: 23.16 | C15: SEK/litre | D15: Current Sweden diesel price, updated 2026-04-13
A16: Other / user-defined fuel price | B16: 20 | C16: SEK/litre | D16: Editable placeholder for other fuel types
A17: Annual inflation rate | B17: 0.025 | C17: Default 3% | D17: Applied with monthly compounding
A18: Annual discount rate | B18: 0.05 | C18: Default 5% | D18: Opportunity cost of capital; monthly discounting
A19: Monthly inflation rate (effective) | B19: =(1+B17)^(1/12)-1 -> 0.0020598363 | C19: Formula | D19: Monthly effective inflation formula: (1+annual inflation)^(1/12)-1
A20: Monthly discount rate (effective) | B20: =(1+B18)^(1/12)-1 -> 0.0040741238 | C20: Formula | D20: Monthly effective discount formula: (1+annual discount)^(1/12)-1
A21: Time horizon | B21: 120 | C21: Months (fixed) | D21: 10 years × 12 months

Sheet Maintenance
A1: Maintenance Planner – editable task list (months override km)
A2: How to use | B2: Enter the maintenance task, base cost, and either months until first due or km until first due. If both are entered, months is used. Repeat interval can also be entered in months or km. The Cashflow sheet automatically schedules recurring events over the 120-month horizon and inflates each cost to the event month.
A3: Note | B3: Default rows below are editable. Blank rows are included so you can add more tasks without breaking the model. The derived columns on the right convert km-based inputs into months using the effective monthly mileage from the Inputs sheet.
A5: Maintenance task | B5: Task category | C5: Estimated cost | D5: First due in months | E5: First due in km | F5: Repeat every X months | G5: Repeat every X km | H5: Notes | I5: Derived 1st month | J5: Derived repeat (months)
A6: Timing belt change | B6: Major service | C6: 8500 | D6: 80 | E6: 60000 | F6: 60 | G6: 90000 | H6: Long interval; depends on engine/service history | I6: =IF(A6="","",IF(D6<>"",MAX(1,ROUNDUP(D6,0)),IF(AND(E6<>"",Inputs!$B$7>0),MAX(1,ROUNDUP(E6/Inputs!$B$7,0)),""))) -> 80 | J6: =IF(A6="","",IF(F6<>"",MAX(1,ROUNDUP(F6,0)),IF(AND(G6<>"",Inputs!$B$7>0),MAX(1,ROUNDUP(G6/Inputs!$B$7,0)),""))) -> 60
A7: Brake pads / brakes | B7: Safety | C7: 5000 | D7: 24 | E7: 30000 | F7: 24 | G7: 30000 | H7: Pads/discs; highly usage dependent | I7: =IF(A7="","",IF(D7<>"",MAX(1,ROUNDUP(D7,0)),IF(AND(E7<>"",Inputs!$B$7>0),MAX(1,ROUNDUP(E7/Inputs!$B$7,0)),""))) -> 24 | J7: =IF(A7="","",IF(F7<>"",MAX(1,ROUNDUP(F7,0)),IF(AND(G7<>"",Inputs!$B$7>0),MAX(1,ROUNDUP(G7/Inputs!$B$7,0)),""))) -> 24
A8: Oil change | B8: Routine service | C8: 1800 | E8: 4000 | F8: 5 | G8: 5000 | H8: Conventional used-car assumption | I8: =IF(A8="","",IF(D8<>"",MAX(1,ROUNDUP(D8,0)),IF(AND(E8<>"",Inputs!$B$7>0),MAX(1,ROUNDUP(E8/Inputs!$B$7,0)),""))) -> 4 | J8: =IF(A8="","",IF(F8<>"",MAX(1,ROUNDUP(F8,0)),IF(AND(G8<>"",Inputs!$B$7>0),MAX(1,ROUNDUP(G8/Inputs!$B$7,0)),""))) -> 5
A9: Front tyres replacement | B9: Tyres | C9: 5000 | D9: 36 | E9: 40000 | F9: 36 | G9: 40000 | H9: Set of front tyres | I9: =IF(A9="","",IF(D9<>"",MAX(1,ROUNDUP(D9,0)),IF(AND(E9<>"",Inputs!$B$7>0),MAX(1,ROUNDUP(E9/Inputs!$B$7,0)),""))) -> 36 | J9: =IF(A9="","",IF(F9<>"",MAX(1,ROUNDUP(F9,0)),IF(AND(G9<>"",Inputs!$B$7>0),MAX(1,ROUNDUP(G9/Inputs!$B$7,0)),""))) -> 36
A10: Rear tyres replacement | B10: Tyres | C10: 4500 | D10: 48 | E10: 50000 | F10: 48 | G10: 50000 | H10: Set of rear tyres | I10: =IF(A10="","",IF(D10<>"",MAX(1,ROUNDUP(D10,0)),IF(AND(E10<>"",Inputs!$B$7>0),MAX(1,ROUNDUP(E10/Inputs!$B$7,0)),""))) -> 48 | J10: =IF(A10="","",IF(F10<>"",MAX(1,ROUNDUP(F10,0)),IF(AND(G10<>"",Inputs!$B$7>0),MAX(1,ROUNDUP(G10/Inputs!$B$7,0)),""))) -> 48
A11: Car wash / detailing | B11: Care | C11: 500 | D11: 1 | F11: 1 | H11: Regular wash/detailing reserve | I11: =IF(A11="","",IF(D11<>"",MAX(1,ROUNDUP(D11,0)),IF(AND(E11<>"",Inputs!$B$7>0),MAX(1,ROUNDUP(E11/Inputs!$B$7,0)),""))) -> 1 | J11: =IF(A11="","",IF(F11<>"",MAX(1,ROUNDUP(F11,0)),IF(AND(G11<>"",Inputs!$B$7>0),MAX(1,ROUNDUP(G11/Inputs!$B$7,0)),""))) -> 1
A12: Battery replacement | B12: Wear item | C12: 2500 | D12: 48 | F12: 60 | H12: Battery life varies with climate/use | I12: =IF(A12="","",IF(D12<>"",MAX(1,ROUNDUP(D12,0)),IF(AND(E12<>"",Inputs!$B$7>0),MAX(1,ROUNDUP(E12/Inputs!$B$7,0)),""))) -> 48 | J12: =IF(A12="","",IF(F12<>"",MAX(1,ROUNDUP(F12,0)),IF(AND(G12<>"",Inputs!$B$7>0),MAX(1,ROUNDUP(G12/Inputs!$B$7,0)),""))) -> 60
A13: Inspection / service | B13: Inspection | C13: 2500 | D13: 12 | E13: 12000 | F13: 12 | G13: 12000 | H13: Annual inspection / service | I13: =IF(A13="","",IF(D13<>"",MAX(1,ROUNDUP(D13,0)),IF(AND(E13<>"",Inputs!$B$7>0),MAX(1,ROUNDUP(E13/Inputs!$B$7,0)),""))) -> 12 | J13: =IF(A13="","",IF(F13<>"",MAX(1,ROUNDUP(F13,0)),IF(AND(G13<>"",Inputs!$B$7>0),MAX(1,ROUNDUP(G13/Inputs!$B$7,0)),""))) -> 12
A14: Wiper blades | B14: Wear item | C14: 350 | D14: 12 | F14: 12 | H14: Annual replacement | I14: =IF(A14="","",IF(D14<>"",MAX(1,ROUNDUP(D14,0)),IF(AND(E14<>"",Inputs!$B$7>0),MAX(1,ROUNDUP(E14/Inputs!$B$7,0)),""))) -> 12 | J14: =IF(A14="","",IF(F14<>"",MAX(1,ROUNDUP(F14,0)),IF(AND(G14<>"",Inputs!$B$7>0),MAX(1,ROUNDUP(G14/Inputs!$B$7,0)),""))) -> 12
A15: Air filter / cabin filter | B15: Routine service | C15: 700 | D15: 12 | E15: 12000 | F15: 12 | G15: 12000 | H15: Common service item | I15: =IF(A15="","",IF(D15<>"",MAX(1,ROUNDUP(D15,0)),IF(AND(E15<>"",Inputs!$B$7>0),MAX(1,ROUNDUP(E15/Inputs!$B$7,0)),""))) -> 12 | J15: =IF(A15="","",IF(F15<>"",MAX(1,ROUNDUP(F15,0)),IF(AND(G15<>"",Inputs!$B$7>0),MAX(1,ROUNDUP(G15/Inputs!$B$7,0)),""))) -> 12
A16: Unexpected repairs reserve | B16: Reserve | C16: 3000 | D16: 18 | F16: 24 | H16: Reserve for miscellaneous repairs | I16: =IF(A16="","",IF(D16<>"",MAX(1,ROUNDUP(D16,0)),IF(AND(E16<>"",Inputs!$B$7>0),MAX(1,ROUNDUP(E16/Inputs!$B$7,0)),""))) -> 18 | J16: =IF(A16="","",IF(F16<>"",MAX(1,ROUNDUP(F16,0)),IF(AND(G16<>"",Inputs!$B$7>0),MAX(1,ROUNDUP(G16/Inputs!$B$7,0)),""))) -> 24
I17: =IF(A17="","",IF(D17<>"",MAX(1,ROUNDUP(D17,0)),IF(AND(E17<>"",Inputs!$B$7>0),MAX(1,ROUNDUP(E17/Inputs!$B$7,0)),""))) | J17: =IF(A17="","",IF(F17<>"",MAX(1,ROUNDUP(F17,0)),IF(AND(G17<>"",Inputs!$B$7>0),MAX(1,ROUNDUP(G17/Inputs!$B$7,0)),"")))
I18: =IF(A18="","",IF(D18<>"",MAX(1,ROUNDUP(D18,0)),IF(AND(E18<>"",Inputs!$B$7>0),MAX(1,ROUNDUP(E18/Inputs!$B$7,0)),""))) | J18: =IF(A18="","",IF(F18<>"",MAX(1,ROUNDUP(F18,0)),IF(AND(G18<>"",Inputs!$B$7>0),MAX(1,ROUNDUP(G18/Inputs!$B$7,0)),"")))
I19: =IF(A19="","",IF(D19<>"",MAX(1,ROUNDUP(D19,0)),IF(AND(E19<>"",Inputs!$B$7>0),MAX(1,ROUNDUP(E19/Inputs!$B$7,0)),""))) | J19: =IF(A19="","",IF(F19<>"",MAX(1,ROUNDUP(F19,0)),IF(AND(G19<>"",Inputs!$B$7>0),MAX(1,ROUNDUP(G19/Inputs!$B$7,0)),"")))
I20: =IF(A20="","",IF(D20<>"",MAX(1,ROUNDUP(D20,0)),IF(AND(E20<>"",Inputs!$B$7>0),MAX(1,ROUNDUP(E20/Inputs!$B$7,0)),""))) | J20: =IF(A20="","",IF(F20<>"",MAX(1,ROUNDUP(F20,0)),IF(AND(G20<>"",Inputs!$B$7>0),MAX(1,ROUNDUP(G20/Inputs!$B$7,0)),"")))
I21: =IF(A21="","",IF(D21<>"",MAX(1,ROUNDUP(D21,0)),IF(AND(E21<>"",Inputs!$B$7>0),MAX(1,ROUNDUP(E21/Inputs!$B$7,0)),""))) | J21: =IF(A21="","",IF(F21<>"",MAX(1,ROUNDUP(F21,0)),IF(AND(G21<>"",Inputs!$B$7>0),MAX(1,ROUNDUP(G21/Inputs!$B$7,0)),"")))
I22: =IF(A22="","",IF(D22<>"",MAX(1,ROUNDUP(D22,0)),IF(AND(E22<>"",Inputs!$B$7>0),MAX(1,ROUNDUP(E22/Inputs!$B$7,0)),""))) | J22: =IF(A22="","",IF(F22<>"",MAX(1,ROUNDUP(F22,0)),IF(AND(G22<>"",Inputs!$B$7>0),MAX(1,ROUNDUP(G22/Inputs!$B$7,0)),"")))
I23: =IF(A23="","",IF(D23<>"",MAX(1,ROUNDUP(D23,0)),IF(AND(E23<>"",Inputs!$B$7>0),MAX(1,ROUNDUP(E23/Inputs!$B$7,0)),""))) | J23: =IF(A23="","",IF(F23<>"",MAX(1,ROUNDUP(F23,0)),IF(AND(G23<>"",Inputs!$B$7>0),MAX(1,ROUNDUP(G23/Inputs!$B$7,0)),"")))
I24: =IF(A24="","",IF(D24<>"",MAX(1,ROUNDUP(D24,0)),IF(AND(E24<>"",Inputs!$B$7>0),MAX(1,ROUNDUP(E24/Inputs!$B$7,0)),""))) | J24: =IF(A24="","",IF(F24<>"",MAX(1,ROUNDUP(F24,0)),IF(AND(G24<>"",Inputs!$B$7>0),MAX(1,ROUNDUP(G24/Inputs!$B$7,0)),"")))
I25: =IF(A25="","",IF(D25<>"",MAX(1,ROUNDUP(D25,0)),IF(AND(E25<>"",Inputs!$B$7>0),MAX(1,ROUNDUP(E25/Inputs!$B$7,0)),""))) | J25: =IF(A25="","",IF(F25<>"",MAX(1,ROUNDUP(F25,0)),IF(AND(G25<>"",Inputs!$B$7>0),MAX(1,ROUNDUP(G25/Inputs!$B$7,0)),"")))
I26: =IF(A26="","",IF(D26<>"",MAX(1,ROUNDUP(D26,0)),IF(AND(E26<>"",Inputs!$B$7>0),MAX(1,ROUNDUP(E26/Inputs!$B$7,0)),""))) | J26: =IF(A26="","",IF(F26<>"",MAX(1,ROUNDUP(F26,0)),IF(AND(G26<>"",Inputs!$B$7>0),MAX(1,ROUNDUP(G26/Inputs!$B$7,0)),"")))
I27: =IF(A27="","",IF(D27<>"",MAX(1,ROUNDUP(D27,0)),IF(AND(E27<>"",Inputs!$B$7>0),MAX(1,ROUNDUP(E27/Inputs!$B$7,0)),""))) | J27: =IF(A27="","",IF(F27<>"",MAX(1,ROUNDUP(F27,0)),IF(AND(G27<>"",Inputs!$B$7>0),MAX(1,ROUNDUP(G27/Inputs!$B$7,0)),"")))
I28: =IF(A28="","",IF(D28<>"",MAX(1,ROUNDUP(D28,0)),IF(AND(E28<>"",Inputs!$B$7>0),MAX(1,ROUNDUP(E28/Inputs!$B$7,0)),""))) | J28: =IF(A28="","",IF(F28<>"",MAX(1,ROUNDUP(F28,0)),IF(AND(G28<>"",Inputs!$B$7>0),MAX(1,ROUNDUP(G28/Inputs!$B$7,0)),"")))
... I55: =IF(A55="","",IF(D55<>"",MAX(1,ROUNDUP(D55,0)),IF(AND(E55<>"",Inputs!$B$7>0),MAX(1,ROUNDUP(E55/Inputs!$B$7,0)),""))) | J55: =IF(A55="","",IF(F55<>"",MAX(1,ROUNDUP(F55,0)),IF(AND(G55<>"",Inputs!$B$7>0),MAX(1,ROUNDUP(G55/Inputs!$B$7,0)),"")))

Sheet Cashflow
A1: Monthly Cashflow Schedule – 10-year used car ownership model
A2: Sign convention | B2: All ownership costs are shown as negative cashflows. The cumulative cost columns convert these to positive running costs for readability.
A3: Logic | B3: Fuel, insurance, tax, and maintenance inflate monthly using the effective monthly inflation rate derived from the annual assumption. Discount factors use the effective monthly discount rate derived from the annual opportunity cost of capital.
A5: Month | B5: Date | C5: Monthly mileage | D5: Purchase price | E5: Fuel cost | F5: Insurance cost | G5: Annual tax | H5: Maintenance cost | I5: Total nominal cashflow | J5: Discount factor | K5: Present value of cashflow | L5: Cumulative nominal cost | M5: Cumulative discounted cost
A6: 0 | B6: =EDATE(Inputs!$B$5,$A6) -> 46113 | C6: =IF($A6=0,0,Inputs!$B$7) -> 0 | D6: =IF($A6=0,-Inputs!$B$4,0) -> -66000 | E6: =IF($A6=0,0,-$C6*Inputs!$B$12/100*Inputs!$B$13*(1+Inputs!$B$19)^$A6) -> 0 | F6: =IF($A6=0,0,-Inputs!$B$10*(1+Inputs!$B$19)^$A6) -> 0 | G6: =IF(AND($A6>0,MOD($A6,12)=0),-Inputs!$B$9*(1+Inputs!$B$19)^$A6,0) -> 0 | H6: =IF($A6=0,0,-SUMPRODUCT((Maintenance!$A$6:$A$55<>"")*(Maintenance!$I$6:$I$55<>"")*($A6=Maintenance!$I$6:$I$55)*Maintenance!$C$6:$C$55*(1+Inputs!$B$19)^$A6)-SUMPRODUCT((Maintenance!$A$6:$A$55<>"")*(Maintenance!$J$6:$J$55>0)*($A6>Maintenance!$I$6:$I$55)*(IFERROR(MOD($A6-Maintenance!$I$6:$I$55,Maintenance!$J$6:$J$55),1)=0)*Maintenance!$C$6:$C$55*(1+Inputs!$B$19)^$A6)) -> 0 | I6: =SUM(D6:H6) -> -66000 | J6: =1/(1+Inputs!$B$20)^$A6 -> 1 | K6: =I6*J6 -> -66000 | L6: =-SUM($I$6:I6) -> 66000 | M6: =-SUM($K$6:K6) -> 66000
A7: 1 | B7: =EDATE(Inputs!$B$5,$A7) -> 46143 | C7: =IF($A7=0,0,Inputs!$B$7) -> 1200 | D7: =IF($A7=0,-Inputs!$B$4,0) -> 0 | E7: =IF($A7=0,0,-$C7*Inputs!$B$12/100*Inputs!$B$13*(1+Inputs!$B$19)^$A7) -> -1172.41 | F7: =IF($A7=0,0,-Inputs!$B$10*(1+Inputs!$B$19)^$A7) -> -905.86209 | G7: =IF(AND($A7>0,MOD($A7,12)=0),-Inputs!$B$9*(1+Inputs!$B$19)^$A7,0) -> 0 | H7: =IF($A7=0,0,-SUMPRODUCT((Maintenance!$A$6:$A$55<>"")*(Maintenance!$I$6:$I$55<>"")*($A7=Maintenance!$I$6:$I$55)*Maintenance!$C$6:$C$55*(1+Inputs!$B$19)^$A7)-SUMPRODUCT((Maintenance!$A$6:$A$55<>"")*(Maintenance!$J$6:$J$55>0)*($A7>Maintenance!$I$6:$I$55)*(IFERROR(MOD($A7-Maintenance!$I$6:$I$55,Maintenance!$J$6:$J$55),1)=0)*Maintenance!$C$6:$C$55*(1+Inputs!$B$19)^$A7)) -> -501.02992 | I7: =SUM(D7:H7) -> -2579.302 | J7: =1/(1+Inputs!$B$20)^$A7 -> 0.99594241 | K7: =I7*J7 -> -2568.8363 | L7: =-SUM($I$6:I7) -> 68579.302 | M7: =-SUM($K$6:K7) -> 68568.836
A8: 2 | B8: =EDATE(Inputs!$B$5,$A8) -> 46174 | C8: =IF($A8=0,0,Inputs!$B$7) -> 1200 | D8: =IF($A8=0,-Inputs!$B$4,0) -> 0 | E8: =IF($A8=0,0,-$C8*Inputs!$B$12/100*Inputs!$B$13*(1+Inputs!$B$19)^$A8) -> -1174.825 | F8: =IF($A8=0,0,-Inputs!$B$10*(1+Inputs!$B$19)^$A8) -> -907.72802 | G8: =IF(AND($A8>0,MOD($A8,12)=0),-Inputs!$B$9*(1+Inputs!$B$19)^$A8,0) -> 0 | H8: =IF($A8=0,0,-SUMPRODUCT((Maintenance!$A$6:$A$55<>"")*(Maintenance!$I$6:$I$55<>"")*($A8=Maintenance!$I$6:$I$55)*Maintenance!$C$6:$C$55*(1+Inputs!$B$19)^$A8)-SUMPRODUCT((Maintenance!$A$6:$A$55<>"")*(Maintenance!$J$6:$J$55>0)*($A8>Maintenance!$I$6:$I$55)*(IFERROR(MOD($A8-Maintenance!$I$6:$I$55,Maintenance!$J$6:$J$55),1)=0)*Maintenance!$C$6:$C$55*(1+Inputs!$B$19)^$A8)) -> 0 | I8: =SUM(D8:H8) -> -2082.553 | J8: =1/(1+Inputs!$B$20)^$A8 -> 0.99190128 | K8: =I8*J8 -> -2065.687 | L8: =-SUM($I$6:I8) -> 70661.855 | M8: =-SUM($K$6:K8) -> 70634.523
A9: 3 | B9: =EDATE(Inputs!$B$5,$A9) -> 46204 | C9: =IF($A9=0,0,Inputs!$B$7) -> 1200 | D9: =IF($A9=0,-Inputs!$B$4,0) -> 0 | E9: =IF($A9=0,0,-$C9*Inputs!$B$12/100*Inputs!$B$13*(1+Inputs!$B$19)^$A9) -> -1177.2449 | F9: =IF($A9=0,0,-Inputs!$B$10*(1+Inputs!$B$19)^$A9) -> -909.59779 | G9: =IF(AND($A9>0,MOD($A9,12)=0),-Inputs!$B$9*(1+Inputs!$B$19)^$A9,0) -> 0 | H9: =IF($A9=0,0,-SUMPRODUCT((Maintenance!$A$6:$A$55<>"")*(Maintenance!$I$6:$I$55<>"")*($A9=Maintenance!$I$6:$I$55)*Maintenance!$C$6:$C$55*(1+Inputs!$B$19)^$A9)-SUMPRODUCT((Maintenance!$A$6:$A$55<>"")*(Maintenance!$J$6:$J$55>0)*($A9>Maintenance!$I$6:$I$55)*(IFERROR(MOD($A9-Maintenance!$I$6:$I$55,Maintenance!$J$6:$J$55),1)=0)*Maintenance!$C$6:$C$55*(1+Inputs!$B$19)^$A9)) -> 0 | I9: =SUM(D9:H9) -> -2086.8427 | J9: =1/(1+Inputs!$B$20)^$A9 -> 0.98787655 | K9: =I9*J9 -> -2061.543 | L9: =-SUM($I$6:I9) -> 72748.698 | M9: =-SUM($K$6:K9) -> 72696.066
A10: 4 | B10: =EDATE(Inputs!$B$5,$A10) -> 46235 | C10: =IF($A10=0,0,Inputs!$B$7) -> 1200 | D10: =IF($A10=0,-Inputs!$B$4,0) -> 0 | E10: =IF($A10=0,0,-$C10*Inputs!$B$12/100*Inputs!$B$13*(1+Inputs!$B$19)^$A10) -> -1179.6699 | F10: =IF($A10=0,0,-Inputs!$B$10*(1+Inputs!$B$19)^$A10) -> -911.47141 | G10: =IF(AND($A10>0,MOD($A10,12)=0),-Inputs!$B$9*(1+Inputs!$B$19)^$A10,0) -> 0 | H10: =IF($A10=0,0,-SUMPRODUCT((Maintenance!$A$6:$A$55<>"")*(Maintenance!$I$6:$I$55<>"")*($A10=Maintenance!$I$6:$I$55)*Maintenance!$C$6:$C$55*(1+Inputs!$B$19)^$A10)-SUMPRODUCT((Maintenance!$A$6:$A$55<>"")*(Maintenance!$J$6:$J$55>0)*($A10>Maintenance!$I$6:$I$55)*(IFERROR(MOD($A10-Maintenance!$I$6:$I$55,Maintenance!$J$6:$J$55),1)=0)*Maintenance!$C$6:$C$55*(1+Inputs!$B$19)^$A10)) -> -1814.8767 | I10: =SUM(D10:H10) -> -3906.018 | J10: =1/(1+Inputs!$B$20)^$A10 -> 0.98386815 | K10: =I10*J10 -> -3843.0067 | L10: =-SUM($I$6:I10) -> 76654.716 | M10: =-SUM($K$6:K10) -> 76539.073
A11: 5 | B11: =EDATE(Inputs!$B$5,$A11) -> 46266 | C11: =IF($A11=0,0,Inputs!$B$7) -> 1200 | D11: =IF($A11=0,-Inputs!$B$4,0) -> 0 | E11: =IF($A11=0,0,-$C11*Inputs!$B$12/100*Inputs!$B$13*(1+Inputs!$B$19)^$A11) -> -1182.0998 | F11: =IF($A11=0,0,-Inputs!$B$10*(1+Inputs!$B$19)^$A11) -> -913.3489 | G11: =IF(AND($A11>0,MOD($A11,12)=0),-Inputs!$B$9*(1+Inputs!$B$19)^$A11,0) -> 0 | H11: =IF($A11=0,0,-SUMPRODUCT((Maintenance!$A$6:$A$55<>"")*(Maintenance!$I$6:$I$55<>"")*($A11=Maintenance!$I$6:$I$55)*Maintenance!$C$6:$C$55*(1+Inputs!$B$19)^$A11)-SUMPRODUCT((Maintenance!$A$6:$A$55<>"")*(Maintenance!$J$6:$J$55>0)*($A11>Maintenance!$I$6:$I$55)*(IFERROR(MOD($A11-Maintenance!$I$6:$I$55,Maintenance!$J$6:$J$55),1)=0)*Maintenance!$C$6:$C$55*(1+Inputs!$B$19)^$A11)) -> -2323.7859 | I11: =SUM(D11:H11) -> -4419.2346 | J11: =1/(1+Inputs!$B$20)^$A11 -> 0.97987601 | K11: =I11*J11 -> -4330.302 | L11: =-SUM($I$6:I11) -> 81073.95 | M11: =-SUM($K$6:K11) -> 80869.375
A12: 6 | B12: =EDATE(Inputs!$B$5,$A12) -> 46296 | C12: =IF($A12=0,0,Inputs!$B$7) -> 1200 | D12: =IF($A12=0,-Inputs!$B$4,0) -> 0 | E12: =IF($A12=0,0,-$C12*Inputs!$B$12/100*Inputs!$B$13*(1+Inputs!$B$19)^$A12) -> -1184.5347 | F12: =IF($A12=0,0,-Inputs!$B$10*(1+Inputs!$B$19)^$A12) -> -915.23024 | G12: =IF(AND($A12>0,MOD($A12,12)=0),-Inputs!$B$9*(1+Inputs!$B$19)^$A12,0) -> 0 | H12: =IF($A12=0,0,-SUMPRODUCT((Maintenance!$A$6:$A$55<>"")*(Maintenance!$I$6:$I$55<>"")*($A12=Maintenance!$I$6:$I$55)*Maintenance!$C$6:$C$55*(1+Inputs!$B$19)^$A12)-SUMPRODUCT((Maintenance!$A$6:$A$55<>"")*(Maintenance!$J$6:$J$55>0)*($A12>Maintenance!$I$6:$I$55)*(IFERROR(MOD($A12-Maintenance!$I$6:$I$55,Maintenance!$J$6:$J$55),1)=0)*Maintenance!$C$6:$C$55*(1+Inputs!$B$19)^$A12)) -> 0 | I12: =SUM(D12:H12) -> -2099.765 | J12: =1/(1+Inputs!$B$20)^$A12 -> 0.97590007 | K12: =I12*J12 -> -2049.1608 | L12: =-SUM($I$6:I12) -> 83173.715 | M12: =-SUM($K$6:K12) -> 82918.536
A13: 7 | B13: =EDATE(Inputs!$B$5,$A13) -> 46327 | C13: =IF($A13=0,0,Inputs!$B$7) -> 1200 | D13: =IF($A13=0,-Inputs!$B$4,0) -> 0 | E13: =IF($A13=0,0,-$C13*Inputs!$B$12/100*Inputs!$B$13*(1+Inputs!$B$19)^$A13) -> -1186.9747 | F13: =IF($A13=0,0,-Inputs!$B$10*(1+Inputs!$B$19)^$A13) -> -917.11547 | G13: =IF(AND($A13>0,MOD($A13,12)=0),-Inputs!$B$9*(1+Inputs!$B$19)^$A13,0) -> 0 | H13: =IF($A13=0,0,-SUMPRODUCT((Maintenance!$A$6:$A$55<>"")*(Maintenance!$I$6:$I$55<>"")*($A13=Maintenance!$I$6:$I$55)*Maintenance!$C$6:$C$55*(1+Inputs!$B$19)^$A13)-SUMPRODUCT((Maintenance!$A$6:$A$55<>"")*(Maintenance!$J$6:$J$55>0)*($A13>Maintenance!$I$6:$I$55)*(IFERROR(MOD($A13-Maintenance!$I$6:$I$55,Maintenance!$J$6:$J$55),1)=0)*Maintenance!$C$6:$C$55*(1+Inputs!$B$19)^$A13)) -> 0 | I13: =SUM(D13:H13) -> -2104.0901 | J13: =1/(1+Inputs!$B$20)^$A13 -> 0.97194027 | K13: =I13*J13 -> -2045.0499 | L13: =-SUM($I$6:I13) -> 85277.805 | M13: =-SUM($K$6:K13) -> 84963.586
A14: 8 | B14: =EDATE(Inputs!$B$5,$A14) -> 46357 | C14: =IF($A14=0,0,Inputs!$B$7) -> 1200 | D14: =IF($A14=0,-Inputs!$B$4,0) -> 0 | E14: =IF($A14=0,0,-$C14*Inputs!$B$12/100*Inputs!$B$13*(1+Inputs!$B$19)^$A14) -> -1189.4196 | F14: =IF($A14=0,0,-Inputs!$B$10*(1+Inputs!$B$19)^$A14) -> -919.00458 | G14: =IF(AND($A14>0,MOD($A14,12)=0),-Inputs!$B$9*(1+Inputs!$B$19)^$A14,0) -> 0 | H14: =IF($A14=0,0,-SUMPRODUCT((Maintenance!$A$6:$A$55<>"")*(Maintenance!$I$6:$I$55<>"")*($A14=Maintenance!$I$6:$I$55)*Maintenance!$C$6:$C$55*(1+Inputs!$B$19)^$A14)-SUMPRODUCT((Maintenance!$A$6:$A$55<>"")*(Maintenance!$J$6:$J$55>0)*($A14>Maintenance!$I$6:$I$55)*(IFERROR(MOD($A14-Maintenance!$I$6:$I$55,Maintenance!$J$6:$J$55),1)=0)*Maintenance!$C$6:$C$55*(1+Inputs!$B$19)^$A14)) -> 0 | I14: =SUM(D14:H14) -> -2108.4242 | J14: =1/(1+Inputs!$B$20)^$A14 -> 0.96799653 | K14: =I14*J14 -> -2040.9473 | L14: =-SUM($I$6:I14) -> 87386.23 | M14: =-SUM($K$6:K14) -> 87004.533
A15: 9 | B15: =EDATE(Inputs!$B$5,$A15) -> 46388 | C15: =IF($A15=0,0,Inputs!$B$7) -> 1200 | D15: =IF($A15=0,-Inputs!$B$4,0) -> 0 | E15: =IF($A15=0,0,-$C15*Inputs!$B$12/100*Inputs!$B$13*(1+Inputs!$B$19)^$A15) -> -1191.8696 | F15: =IF($A15=0,0,-Inputs!$B$10*(1+Inputs!$B$19)^$A15) -> -920.89758 | G15: =IF(AND($A15>0,MOD($A15,12)=0),-Inputs!$B$9*(1+Inputs!$B$19)^$A15,0) -> 0 | H15: =IF($A15=0,0,-SUMPRODUCT((Maintenance!$A$6:$A$55<>"")*(Maintenance!$I$6:$I$55<>"")*($A15=Maintenance!$I$6:$I$55)*Maintenance!$C$6:$C$55*(1+Inputs!$B$19)^$A15)-SUMPRODUCT((Maintenance!$A$6:$A$55<>"")*(Maintenance!$J$6:$J$55>0)*($A15>Maintenance!$I$6:$I$55)*(IFERROR(MOD($A15-Maintenance!$I$6:$I$55,Maintenance!$J$6:$J$55),1)=0)*Maintenance!$C$6:$C$55*(1+Inputs!$B$19)^$A15)) -> 0 | I15: =SUM(D15:H15) -> -2112.7672 | J15: =1/(1+Inputs!$B$20)^$A15 -> 0.96406879 | K15: =I15*J15 -> -2036.853 | L15: =-SUM($I$6:I15) -> 89498.997 | M15: =-SUM($K$6:K15) -> 89041.386
A16: 10 | B16: =EDATE(Inputs!$B$5,$A16) -> 46419 | C16: =IF($A16=0,0,Inputs!$B$7) -> 1200 | D16: =IF($A16=0,-Inputs!$B$4,0) -> 0 | E16: =IF($A16=0,0,-$C16*Inputs!$B$12/100*Inputs!$B$13*(1+Inputs!$B$19)^$A16) -> -1194.3247 | F16: =IF($A16=0,0,-Inputs!$B$10*(1+Inputs!$B$19)^$A16) -> -922.79447 | G16: =IF(AND($A16>0,MOD($A16,12)=0),-Inputs!$B$9*(1+Inputs!$B$19)^$A16,0) -> 0 | H16: =IF($A16=0,0,-SUMPRODUCT((Maintenance!$A$6:$A$55<>"")*(Maintenance!$I$6:$I$55<>"")*($A16=Maintenance!$I$6:$I$55)*Maintenance!$C$6:$C$55*(1+Inputs!$B$19)^$A16)-SUMPRODUCT((Maintenance!$A$6:$A$55<>"")*(Maintenance!$J$6:$J$55>0)*($A16>Maintenance!$I$6:$I$55)*(IFERROR(MOD($A16-Maintenance!$I$6:$I$55,Maintenance!$J$6:$J$55),1)=0)*Maintenance!$C$6:$C$55*(1+Inputs!$B$19)^$A16)) -> 0 | I16: =SUM(D16:H16) -> -2117.1192 | J16: =1/(1+Inputs!$B$20)^$A16 -> 0.960157 | K16: =I16*J16 -> -2032.7668 | L16: =-SUM($I$6:I16) -> 91616.116 | M16: =-SUM($K$6:K16) -> 91074.153
A17: 11 | B17: =EDATE(Inputs!$B$5,$A17) -> 46447 | C17: =IF($A17=0,0,Inputs!$B$7) -> 1200 | D17: =IF($A17=0,-Inputs!$B$4,0) -> 0 | E17: =IF($A17=0,0,-$C17*Inputs!$B$12/100*Inputs!$B$13*(1+Inputs!$B$19)^$A17) -> -1196.7848 | F17: =IF($A17=0,0,-Inputs!$B$10*(1+Inputs!$B$19)^$A17) -> -924.69528 | G17: =IF(AND($A17>0,MOD($A17,12)=0),-Inputs!$B$9*(1+Inputs!$B$19)^$A17,0) -> 0 | H17: =IF($A17=0,0,-SUMPRODUCT((Maintenance!$A$6:$A$55<>"")*(Maintenance!$I$6:$I$55<>"")*($A17=Maintenance!$I$6:$I$55)*Maintenance!$C$6:$C$55*(1+Inputs!$B$19)^$A17)-SUMPRODUCT((Maintenance!$A$6:$A$55<>"")*(Maintenance!$J$6:$J$55>0)*($A17>Maintenance!$I$6:$I$55)*(IFERROR(MOD($A17-Maintenance!$I$6:$I$55,Maintenance!$J$6:$J$55),1)=0)*Maintenance!$C$6:$C$55*(1+Inputs!$B$19)^$A17)) -> 0 | I17: =SUM(D17:H17) -> -2121.4801 | J17: =1/(1+Inputs!$B$20)^$A17 -> 0.95626107 | K17: =I17*J17 -> -2028.6888 | L17: =-SUM($I$6:I17) -> 93737.596 | M17: =-SUM($K$6:K17) -> 93102.841
... A126: 120 | B126: =EDATE(Inputs!$B$5,$A126) -> 49766 | C126: =IF($A126=0,0,Inputs!$B$7) -> 1200 | D126: =IF($A126=0,-Inputs!$B$4,0) -> 0 | E126: =IF($A126=0,0,-$C126*Inputs!$B$12/100*Inputs!$B$13*(1+Inputs!$B$19)^$A126) -> -1497.6989 | F126: =IF($A126=0,0,-Inputs!$B$10*(1+Inputs!$B$19)^$A126) -> -1157.1964 | G126: =IF(AND($A126>0,MOD($A126,12)=0),-Inputs!$B$9*(1+Inputs!$B$19)^$A126,0) -> -1600.1057 | H126: =IF($A126=0,0,-SUMPRODUCT((Maintenance!$A$6:$A$55<>"")*(Maintenance!$I$6:$I$55<>"")*($A126=Maintenance!$I$6:$I$55)*Maintenance!$C$6:$C$55*(1+Inputs!$B$19)^$A126)-SUMPRODUCT((Maintenance!$A$6:$A$55<>"")*(Maintenance!$J$6:$J$55>0)*($A126>Maintenance!$I$6:$I$55)*(IFERROR(MOD($A126-Maintenance!$I$6:$I$55,Maintenance!$J$6:$J$55),1)=0)*Maintenance!$C$6:$C$55*(1+Inputs!$B$19)^$A126)) -> 0 | I126: =SUM(D126:H126) -> -4255.001 | J126: =1/(1+Inputs!$B$20)^$A126 -> 0.61391325 | K126: =I126*J126 -> -2612.2015 | L126: =-SUM($I$6:I126) -> 402722.59 | M126: =-SUM($K$6:K126) -> 331847.88

Sheet Help - Prompt
A1: Help & research prompt
A3: 1. How to use this workbook
A4: Step 1 | B4: Go to the Inputs sheet and update the yellow cells: car price, tax, insurance, fuel type, fuel consumption, fuel price, inflation, and discount rate.
A5: Step 2 | B5: If you are not sure about mileage, leave the monthly mileage input blank. The model will automatically use 1,000 km/month (12,000 km/year).
A6: Step 3 | B6: Review the Maintenance sheet. Edit the default task list, base costs, and timing. You can enter either months or km for the first due date and repeat interval. If both are entered, months takes priority.
A7: Step 4 | B7: Open the Cashflow sheet to review the full 120-month schedule. Month 0 contains the purchase price. All other cost items inflate monthly and are discounted back to present value.
A8: Step 5 | B8: Use the Dashboard sheet for summary metrics and charts. The discounted total cost is the present-value cost of owning the car over the full holding period.
A9: 2. Practical notes
A10: Tax timing | B10: This template applies annual vehicle tax at months 12, 24, ..., 120. If your timing differs, you can edit the Annual tax formula on the Cashflow sheet.
A11: Fuel defaults | B11: Default petrol and diesel prices were populated from current Sweden price sources and remain fully editable. If you prefer local pump prices, overwrite the default price cells on Inputs.
A12: Maintenance inflation | B12: Maintenance costs are entered in today's SEK and inflated to the month when each event occurs.
A13: 3. Suggested prompt to research Sweden maintenance costs
A15: Please estimate current maintenance and repair costs in Sweden for this used car: [make, model, year, engine, fuel type, mileage, transmission, driven wheels]. I want realistic independent-workshop or common market estimates in SEK, with price ranges where possible. Please provide estimated costs for: • oil change • timing belt / timing chain service (if relevant) • front brake pads / discs • rear brake pads / discs • front tyres • rear tyres • battery replacement • annual inspection / routine service • wiper blades • air filter / cabin filter • common unexpected repairs for this model in Sweden For each item, please also note how often it typically occurs, either in months/years or km, and mention any Sweden-specific factors such as winter tyres, corrosion, road salt, inspection rules, or typical labour rates. If possible, distinguish between low, mid, and high cost scenarios and flag items that are model-specific or engine-specific.
A30: Fuel price sources used for default inputs
A31: Gasoline | B31: https://www.globalpetrolprices.com/Sweden/gasoline_prices/
A32: Diesel | B32: https://www.globalpetrolprices.com/Sweden/diesel_prices/
A33: Excel note | B33: Excel does not allow '/' in sheet names, so this tab is named 'Help - Prompt' instead of 'Help / Prompt'.
